{
  "$schema" : "http://json-schema.org/draft-07/schema#",
  "$id" : "AWS_RDS_DBClusterResource.schema.json",
  "title" : "DBClusterResource",
  "description" : "http://docs.aws.amazon.com/AWSCloudFormation/latest/UserGuide/aws-resource-rds-dbcluster.html",
  "type" : "object",
  "extends" : {
    "$ref" : "Resource.schema.json"
  },
  "javaType" : "aws.rds.DBClusterResource",
  "javaInterfaces" : [ "aws.HasAttributes<DBClusterAttributes>" ],
  "properties" : {
    "Properties" : {
      "$ref" : "AWS_RDS_DBCluster.schema.json"
    }
  }
}