{
  "$schema" : "http://json-schema.org/draft-07/schema#",
  "$id" : "AWS_AppSync_ResolverResource.schema.json",
  "title" : "ResolverResource",
  "description" : "http://docs.aws.amazon.com/AWSCloudFormation/latest/UserGuide/aws-resource-appsync-resolver.html",
  "type" : "object",
  "extends" : {
    "$ref" : "Resource.schema.json"
  },
  "javaType" : "aws.appsync.ResolverResource",
  "javaInterfaces" : [ "aws.HasAttributes<ResolverAttributes>" ],
  "properties" : {
    "Properties" : {
      "$ref" : "AWS_AppSync_Resolver.schema.json"
    }
  }
}