{
  "$schema" : "http://json-schema.org/draft-07/schema#",
  "$id" : "AWS_Cognito_UserPoolResourceServerResource.schema.json",
  "title" : "UserPoolResourceServerResource",
  "description" : "http://docs.aws.amazon.com/AWSCloudFormation/latest/UserGuide/aws-resource-cognito-userpoolresourceserver.html",
  "type" : "object",
  "extends" : {
    "$ref" : "Resource.schema.json"
  },
  "javaType" : "shiver.me.timbers.aws.cognito.UserPoolResourceServerResource",
  "javaInterfaces" : [ "shiver.me.timbers.aws.HasDependsOn<UserPoolResourceServerResource>", "shiver.me.timbers.aws.HasCondition<UserPoolResourceServerResource>" ],
  "properties" : {
    "Type" : {
      "type" : "string",
      "default" : "AWS::Cognito::UserPoolResourceServer"
    },
    "Properties" : {
      "$ref" : "AWS_Cognito_UserPoolResourceServer.schema.json"
    }
  }
}